<configs>
    <append xpath="//block[@name='campfire']">
        <property name="DowngradeBlock" value="cntCollapsedCampfire"/>
        <property name="DegradationPerUse" value="1"/>
        <effect_group name="DamageHooks Degrade">
            
            <!-- Don't downgrade each tick that's active. Gate it behind a random roll -->
            <triggered_effect trigger="onSelfItemDegrade" action="DamageBlock, SCore">
                <requirement name="RandomRoll" seed_type="Random" min_max="0,100" operation="LTE" value="10"/>
            </triggered_effect>
        </effect_group>
    </append>
    <append xpath="//block[@name='cntCollapsedCampfire']">
        <property class="UpgradeBlock">
            <property name="ToBlock" value="campfire"/>
            <property name="Item" value="resourceCobblestones"/>
            <property name="ItemCount" value="5"/>
            <property name="UpgradeHitCount" value="4"/>
        </property>
    </append>
    <csv xpath="//block[@name='cntCollapsedCampfire']/property[@name='Extends']/@param1" op="add">DowngradeBlock</csv>

    <append xpath="//block[@name='forge']">
        <property name="DowngradeBlock" value="cntForgeWorkstationBroken"/>
        <property name="DegradationPerUse" value="1"/>
        <effect_group name="DamageHooks Degrade">

            <!-- Don't downgrade each tick that's active. Gate it behind a random roll -->
            <triggered_effect trigger="onSelfItemDegrade" action="DamageBlock, SCore">
                <requirement name="RandomRoll" seed_type="Random" min_max="0,100" operation="LTE" value="10"/>
            </triggered_effect>
        </effect_group>
    </append>
    <append xpath="//block[@name='cntForgeWorkstationBroken']">
        <property class="UpgradeBlock">
            <property name="ToBlock" value="forge"/>
            <property name="Item" value="resourceCobblestones"/>
            <property name="ItemCount" value="15"/>
            <property name="UpgradeHitCount" value="4"/>
        </property>
    </append>

    <append xpath="//block[@name='workbench']">
        <property name="DowngradeBlock" value="cntCollapsedWorkbench"/>
        <effect_group name="DamageHooks Degrade">

            <!-- Don't downgrade each tick that's active. Gate it behind a random roll -->
            <triggered_effect trigger="onSelfItemDegrade" action="DamageBlock, SCore">
                <requirement name="RandomRoll" seed_type="Random" min_max="0,100" operation="LTE" value="10"/>
            </triggered_effect>
        </effect_group>
    </append>
    <append xpath="//block[@name='cntCollapsedWorkbench']">
        <property class="UpgradeBlock">
            <property name="ToBlock" value="workbench"/>
            <property name="Item" value="resourceForgedIron"/>
            <property name="ItemCount" value="10"/>
            <property name="UpgradeHitCount" value="4"/>
        </property>
    </append>

    <append xpath="//block[@name='chemistryStation']">
        <property name="DowngradeBlock" value="cntCollapsedChemistryStation"/>
        <effect_group name="DamageHooks Degrade">

            <!-- Don't downgrade each tick that's active. Gate it behind a random roll -->
            <triggered_effect trigger="onSelfItemDegrade" action="DamageBlock, SCore">
                <requirement name="RandomRoll" seed_type="Random" min_max="0,100" operation="LTE" value="10"/>
            </triggered_effect>
        </effect_group>
    </append>
    <append xpath="//block[@name='cntCollapsedChemistryStation']">
        <property class="UpgradeBlock">
            <property name="ToBlock" value="chemistryStation"/>
            <property name="Item" value="resourceForgedIron"/>
            <property name="ItemCount" value="10"/>
            <property name="UpgradeHitCount" value="4"/>
        </property>
    </append>

    <append xpath="//block[@name='cntDewCollector']">
        <property name="DowngradeBlock" value="cntCollapsedDewCollector"/>
        <effect_group name="DamageHooks Degrade">

            <!-- Don't downgrade each tick that's active. Gate it behind a random roll -->
            <triggered_effect trigger="onSelfItemDegrade" action="DamageBlock, SCore">
                <requirement name="RandomRoll" seed_type="Random" min_max="0,100" operation="LTE" value="10"/>
            </triggered_effect>
        </effect_group>
    </append>
    <append xpath="//block[@name='cntCollapsedDewCollector']">
        <property class="UpgradeBlock">
            <property name="ToBlock" value="cntDewCollector"/>
            <property name="Item" value="resourceScrapPolymers"/>
            <property name="ItemCount" value="10"/>
            <property name="UpgradeHitCount" value="4"/>
        </property>
    </append>

</configs>